pyosys-0.61.dist-info/RECORD
pyosys-0.61.dist-info/WHEEL
pyosys-0.61.dist-info/COPYING
pyosys-0.61.dist-info/top_level.txt
pyosys-0.61.dist-info/METADATA
pyosys/yosys-abc
pyosys/__init__.py
pyosys/libyosys.so
pyosys/generator.py
pyosys/share/cmp2softlogic.v
pyosys/share/techmap.v
pyosys/share/simlib.v
pyosys/share/simcells.v
pyosys/share/cmp2lut.v
pyosys/share/abc9_model.v
pyosys/share/adff2dff.v
pyosys/share/mul2dsp.v
pyosys/share/smtmap.v
pyosys/share/gate2lut.v
pyosys/share/dff2ff.v
pyosys/share/pmux2mux.v
pyosys/share/abc9_map.v
pyosys/share/cmp2lcu.v
pyosys/share/abc9_unmap.v
pyosys/share/intel/common/ff_map.v
pyosys/share/intel/common/altpll_bb.v
pyosys/share/intel/common/brams_map_m9k.v
pyosys/share/intel/common/m9k_bb.v
pyosys/share/intel/common/brams_m9k.txt
pyosys/share/intel/cycloneive/cells_sim.v
pyosys/share/intel/cycloneive/cells_map.v
pyosys/share/intel/cyclone10lp/cells_sim.v
pyosys/share/intel/cyclone10lp/cells_map.v
pyosys/share/intel/cycloneiv/cells_sim.v
pyosys/share/intel/cycloneiv/cells_map.v
pyosys/share/intel/max10/cells_sim.v
pyosys/share/intel/max10/cells_map.v
pyosys/share/xilinx/ff_map.v
pyosys/share/xilinx/cells_sim.v
pyosys/share/xilinx/lutrams_xcv_map.v
pyosys/share/xilinx/brams_xc4v_map.v
pyosys/share/xilinx/brams_xc2v.txt
pyosys/share/xilinx/brams_xc6v_map.v
pyosys/share/xilinx/brams_xcu_map.v
pyosys/share/xilinx/urams.txt
pyosys/share/xilinx/xc4v_dsp_map.v
pyosys/share/xilinx/brams_xc2v_map.v
pyosys/share/xilinx/xcu_dsp_map.v
pyosys/share/xilinx/lutrams_xcu.txt
pyosys/share/xilinx/arith_map.v
pyosys/share/xilinx/lutrams_xcv.txt
pyosys/share/xilinx/cells_xtra.v
pyosys/share/xilinx/lut_map.v
pyosys/share/xilinx/brams_xcv_map.v
pyosys/share/xilinx/abc9_model.v
pyosys/share/xilinx/brams_xc4v.txt
pyosys/share/xilinx/xc7_dsp_map.v
pyosys/share/xilinx/lutrams_xc5v.txt
pyosys/share/xilinx/lutrams_xc5v_map.v
pyosys/share/xilinx/brams_xc5v_map.v
pyosys/share/xilinx/xc3sda_dsp_map.v
pyosys/share/xilinx/mux_map.v
pyosys/share/xilinx/cells_map.v
pyosys/share/xilinx/brams_xc3sda.txt
pyosys/share/xilinx/urams_map.v
