Metadata-Version: 2.1
Name: pyosys
Version: 0.61
Summary: Python access to libyosys
License: MIT
Classifier: Programming Language :: Python :: 3
Classifier: Intended Audience :: Developers
Classifier: Operating System :: POSIX :: Linux
Classifier: Operating System :: MacOS :: MacOS X
Requires-Python: >=3.8
License-File: COPYING
